MANIFEST.in
README.rst
setup.py
edgebox/__init__.py
edgebox/app.yml.tmpl
edgebox/appinsts.yml.tmpl
edgebox/command_line.py
edgebox/edgebox_os.py
edgebox/github.py
edgebox/linux_edgebox.service.tmpl
edgebox/linux_edgebox.timer.tmpl
edgebox/macos_launchagent.plist.tmpl
edgebox/master_controller.py
edgebox/workflow.tmpl
edgebox.egg-info/PKG-INFO
edgebox.egg-info/SOURCES.txt
edgebox.egg-info/dependency_links.txt
edgebox.egg-info/entry_points.txt
edgebox.egg-info/not-zip-safe
edgebox.egg-info/requires.txt
edgebox.egg-info/top_level.txt