Metadata-Version: 1.2
Name: edgebox
Version: 0.12
Summary: Edgebox for MobiledgeX
Home-page: http://github.com/mobiledgex/edgebox
Author: Venky Tumkur
Author-email: venky.tumkur@mobiledgex.com
License: MIT
Platform: UNKNOWN
Requires-Python: >=3.6, <4
